odoo10_addon_hr_employee_calendar_planning-10.0.1.1.0-nspkg.pth
odoo/addons/hr_employee_calendar_planning/README.rst
odoo/addons/hr_employee_calendar_planning/__init__.py
odoo/addons/hr_employee_calendar_planning/__manifest__.py
odoo/addons/hr_employee_calendar_planning/hooks.py
odoo/addons/hr_employee_calendar_planning/i18n/hr_employee_calendar_planning.pot
odoo/addons/hr_employee_calendar_planning/models/__init__.py
odoo/addons/hr_employee_calendar_planning/models/hr_employee.py
odoo/addons/hr_employee_calendar_planning/models/resource_calendar.py
odoo/addons/hr_employee_calendar_planning/readme/CONFIGURE.rst
odoo/addons/hr_employee_calendar_planning/readme/CONTRIBUTORS.rst
odoo/addons/hr_employee_calendar_planning/readme/DESCRIPTION.rst
odoo/addons/hr_employee_calendar_planning/readme/INSTALL.rst
odoo/addons/hr_employee_calendar_planning/readme/ROADMAP.rst
odoo/addons/hr_employee_calendar_planning/security/ir.model.access.csv
odoo/addons/hr_employee_calendar_planning/static/description/icon.png
odoo/addons/hr_employee_calendar_planning/static/description/index.html
odoo/addons/hr_employee_calendar_planning/tests/__init__.py
odoo/addons/hr_employee_calendar_planning/tests/test_hr_employee_calendar_planning.py
odoo/addons/hr_employee_calendar_planning/views/hr_employee_views.xml
odoo/addons/hr_employee_calendar_planning/wizards/__init__.py
odoo/addons/hr_employee_calendar_planning/wizards/wizard_employee_calendar_dates.py
odoo/addons/hr_employee_calendar_planning/wizards/wizard_employee_calendar_views.xml
odoo10_addon_hr_employee_calendar_planning-10.0.1.1.0.dist-info/METADATA
odoo10_addon_hr_employee_calendar_planning-10.0.1.1.0.dist-info/WHEEL
odoo10_addon_hr_employee_calendar_planning-10.0.1.1.0.dist-info/namespace_packages.txt
odoo10_addon_hr_employee_calendar_planning-10.0.1.1.0.dist-info/top_level.txt
odoo10_addon_hr_employee_calendar_planning-10.0.1.1.0.dist-info/RECORD
